{
	"name": "SQL script 3",
	"properties": {
		"content": {
			"query": "SELECT TOP (100) [caseReference]\n,[caseId]\n,[submissionId]\n,[caseStatus]\n,[caseType]\n,[caseProcedure]\n,[lpaCode]\n,[caseOfficerId]\n,[inspectorId]\n,[allocationLevel]\n,[allocationBand]\n,[caseSpecialisms]\n,[caseSubmittedDate]\n,[caseCreatedDate]\n,[caseUpdatedDate]\n,[caseValidDate]\n,[caseValidationDate]\n,[caseValidationOutcome]\n,[caseValidationInvalidDetails]\n,[caseValidationIncompleteDetails]\n,[caseExtensionDate]\n,[caseStartedDate]\n,[casePublishedDate]\n,[linkedCaseStatus]\n,[leadCaseReference]\n,[lpaQuestionnaireDueDate]\n,[lpaQuestionnaireSubmittedDate]\n,[lpaQuestionnaireCreatedDate]\n,[lpaQuestionnairePublishedDate]\n,[lpaQuestionnaireValidationOutcome]\n,[lpaQuestionnaireValidationOutcomeDate]\n,[lpaQuestionnaireValidationDetails]\n,[lpaStatement]\n,[caseWithdrawnDate]\n,[caseTransferredDate]\n,[transferredCaseClosedDate]\n,[caseDecisionOutcomeDate]\n,[caseDecisionPublishedDate]\n,[caseDecisionOutcome]\n,[caseCompletedDate]\n,[enforcementNotice]\n,[applicationReference]\n,[applicationDate]\n,[applicationDecision]\n,[applicationDecisionDate]\n,[caseSubmissionDueDate]\n,[siteAddressLine1]\n,[siteAddressLine2]\n,[siteAddressTown]\n,[siteAddressCounty]\n,[siteAddressPostcode]\n,[siteAccessDetails]\n,[siteSafetyDetails]\n,[siteAreaSquareMetres]\n,[floorSpaceSquareMetres]\n,[isCorrectAppealType]\n,[isGreenBelt]\n,[inConservationArea]\n,[ownsAllLand]\n,[ownsSomeLand]\n,[knowsOtherOwners]\n,[knowsAllOwners]\n,[advertisedAppeal]\n,[notificationMethod]\n,[ownersInformed]\n,[originalDevelopmentDescription]\n,[changedDevelopmentDescription]\n,[newConditionDetails]\n,[nearbyCaseReferences]\n,[neighbouringSiteAddresses]\n,[affectedListedBuildingNumbers]\n,[changedListedBuildingNumbers]\n,[appellantCostsAppliedFor]\n,[lpaCostsAppliedFor]\n,[agriculturalHolding]\n,[tenantAgriculturalHolding]\n,[otherTenantsAgriculturalHolding]\n,[informedTenantsAgriculturalHolding]\n,[appellantProcedurePreference]\n,[appellantProcedurePreferenceDetails]\n,[appellantProcedurePreferenceDuration]\n,[appellantProcedurePreferenceWitnessCount]\n,[statusPlanningObligation]\n,[affectsScheduledMonument]\n,[hasProtectedSpecies]\n,[isAonbNationalLandscape]\n,[designatedSitesNames]\n,[isGypsyOrTravellerSite]\n,[isPublicRightOfWay]\n,[eiaEnvironmentalImpactSchedule]\n,[eiaDevelopmentDescription]\n,[eiaSensitiveAreaDetails]\n,[eiaColumnTwoThreshold]\n,[eiaScreeningOpinion]\n,[eiaRequiresEnvironmentalStatement]\n,[eiaCompletedEnvironmentalStatement]\n,[hasStatutoryConsultees]\n,[consultedBodiesDetails]\n,[hasInfrastructureLevy]\n,[isInfrastructureLevyFormallyAdopted]\n,[infrastructureLevyAdoptedDate]\n,[infrastructureLevyExpectedDate]\n,[lpaProcedurePreference]\n,[lpaProcedurePreferenceDetails]\n,[lpaProcedurePreferenceDuration]\n,[caseworkReason]\n,[developmentType]\n,[importantInformation]\n,[jurisdiction]\n,[redeterminedIndicator]\n,[dateCostsReportDespatched]\n,[dateNotRecoveredOrDerecovered]\n,[dateRecovered]\n,[originalCaseDecisionDate]\n,[targetDate]\n,[appellantCommentsSubmittedDate]\n,[appellantStatementSubmittedDate]\n,[appellantProofsSubmittedDate]\n,[finalCommentsDueDate]\n,[interestedPartyRepsDueDate]\n,[lpaCommentsSubmittedDate]\n,[lpaProofsSubmittedDate]\n,[lpaStatementSubmittedDate]\n,[proofsOfEvidenceDueDate]\n,[siteNoticesSentDate]\n,[statementDueDate]\n,[reasonForNeighbourVisits]\n,[numberOfResidencesNetChange]\n,[siteGridReferenceEasting]\n,[siteGridReferenceNorthing]\n,[siteViewableFromRoad]\n,[siteWithinSSSI]\n,[typeOfPlanningApplication]\n,[preserveGrantLoan]\n,[consultHistoricEngland]\n,[planningObligationDueDate]\n,[statementOfCommonGroundDueDate]\n FROM [odw_curated_db].[dbo].[appeal_s78]",
			"metadata": {
				"language": "sql"
			},
			"currentConnection": {
				"databaseName": "odw_curated_db",
				"poolName": "Built-in"
			},
			"resultLimit": 5000
		},
		"type": "SqlQuery"
	}
}