{
	"name": "pln_green_specialist_case_curated_main",
	"properties": {
		"activities": [
			{
				"name": "setharmonisedstarttime",
				"type": "SetVariable",
				"dependsOn": [],
				"policy": {
					"secureOutput": false,
					"secureInput": false
				},
				"userProperties": [],
				"typeProperties": {
					"variableName": "harmonisedstarttime",
					"value": "@utcNow()"
				}
			},
			{
				"name": "Record loading relevant reps data",
				"type": "ExecutePipeline",
				"dependsOn": [],
				"policy": {
					"secureInput": false
				},
				"userProperties": [],
				"typeProperties": {
					"pipeline": {
						"referenceName": "pln_log_to_appins",
						"type": "PipelineReference"
					},
					"waitOnCompletion": true,
					"parameters": {
						"Stage": "OnProgress",
						"PipelineName": "@pipeline().Pipeline",
						"PipelineRunID": "@pipeline().RunId",
						"StartTime": "@formatDateTime(utcnow(), 'yyyy-MM-ddTHH:mm:ssZ')",
						"StatusMessage": "Loading Green Specialist Case Curated Layer",
						"PipelineTriggerID": "@pipeline().TriggerId",
						"PipelineTriggerName": "@pipeline().TriggerName",
						"PipelineTriggerType": "@pipeline().TriggerType",
						"PipelineTriggeredbyPipelineName": "@pipeline()?.TriggeredByPipelineName",
						"PipelineTriggeredbyPipelineRunID": "@pipeline()?.TriggeredByPipelineRunId",
						"ActivityType": {
							"value": "@pipeline().Pipeline",
							"type": "Expression"
						},
						"AppInsIKey": "@pipeline().parameters.apps_insights_ikey"
					}
				}
			}
		],
		"parameters": {
			"webhook_url": {
				"type": "string"
			},
			"subscription_id": {
				"type": "string"
			},
			"resource_group": {
				"type": "string"
			},
			"starting_colour": {
				"type": "string"
			},
			"on_progress_colour": {
				"type": "string"
			},
			"failed_colour": {
				"type": "string"
			},
			"start_time": {
				"type": "string"
			},
			"starting_image": {
				"type": "string"
			},
			"progress_image": {
				"type": "string"
			},
			"warning_image": {
				"type": "string"
			},
			"failed_image": {
				"type": "string"
			},
			"warning_colour": {
				"type": "string"
			},
			"horizon_feed": {
				"type": "array"
			},
			"apps_insights_ikey": {
				"type": "string"
			}
		},
		"variables": {
			"execution_logs": {
				"type": "String"
			},
			"temp_var": {
				"type": "String"
			},
			"w": {
				"type": "String"
			},
			"errorMsg": {
				"type": "String"
			},
			"wait1": {
				"type": "Integer",
				"defaultValue": 1
			},
			"wait2": {
				"type": "Integer",
				"defaultValue": 2
			},
			"wait3": {
				"type": "Integer",
				"defaultValue": 3
			},
			"wait4": {
				"type": "Integer",
				"defaultValue": 4
			},
			"wait5": {
				"type": "Integer",
				"defaultValue": 5
			},
			"wait6": {
				"type": "Integer",
				"defaultValue": 6
			},
			"wait7": {
				"type": "Integer",
				"defaultValue": 7
			},
			"wait8": {
				"type": "Integer",
				"defaultValue": 8
			},
			"recordCount": {
				"type": "String"
			},
			"error_message": {
				"type": "String"
			},
			"harmonisedstarttime": {
				"type": "String"
			}
		},
		"folder": {
			"name": "green_specialist_case/3-curated"
		},
		"annotations": []
	}
}