{
	"name": "pln_green_specialist_case_odw_src_odw_raw",
	"properties": {
		"activities": [
			{
				"name": "Copy xlsx to odw-raw green_specialist_case",
				"type": "Copy",
				"dependsOn": [],
				"policy": {
					"timeout": "0.12:00:00",
					"retry": 0,
					"retryIntervalInSeconds": 30,
					"secureOutput": false,
					"secureInput": false
				},
				"userProperties": [],
				"typeProperties": {
					"source": {
						"type": "BinarySource",
						"storeSettings": {
							"type": "AzureFileStorageReadSettings",
							"deleteFilesAfterCompletion": true
						},
						"formatSettings": {
							"type": "BinaryReadSettings"
						}
					},
					"sink": {
						"type": "BinarySink",
						"storeSettings": {
							"type": "AzureBlobFSWriteSettings"
						}
					},
					"enableStaging": false
				},
				"inputs": [
					{
						"referenceName": "ds_odwdatalab_green_case_specialist",
						"type": "DatasetReference",
						"parameters": {
							"ds_Folder_Path": {
								"value": "@pipeline().parameters.Folder_Path",
								"type": "Expression"
							},
							"ds_Env_Type": {
								"value": "@if( contains(toLower(pipeline().DataFactory), 'dev'), 'dev', if( contains(toLower(pipeline().DataFactory), 'test'), 'test', 'prod' ) )",
								"type": "Expression"
							}
						}
					}
				],
				"outputs": [
					{
						"referenceName": "ds_odw_raw_greencase_specialist_dest",
						"type": "DatasetReference"
					}
				]
			},
			{
				"name": "Get xlsx File recent folder",
				"type": "GetMetadata",
				"dependsOn": [
					{
						"activity": "Copy xlsx to odw-raw green_specialist_case",
						"dependencyConditions": [
							"Succeeded"
						]
					}
				],
				"policy": {
					"timeout": "0.12:00:00",
					"retry": 0,
					"retryIntervalInSeconds": 30,
					"secureOutput": false,
					"secureInput": false
				},
				"userProperties": [],
				"typeProperties": {
					"dataset": {
						"referenceName": "ds_odw_raw_get_recent_green_specialist_case_folder",
						"type": "DatasetReference"
					},
					"fieldList": [
						"exists"
					],
					"storeSettings": {
						"type": "AzureBlobFSReadSettings",
						"recursive": true,
						"enablePartitionDiscovery": false
					},
					"formatSettings": {
						"type": "BinaryReadSettings"
					}
				}
			},
			{
				"name": "If recent file folder exist",
				"type": "IfCondition",
				"dependsOn": [
					{
						"activity": "Get xlsx File recent folder",
						"dependencyConditions": [
							"Succeeded"
						]
					}
				],
				"userProperties": [],
				"typeProperties": {
					"expression": {
						"value": "@equals(activity('Get xlsx File recent folder').output.exists,true)",
						"type": "Expression"
					},
					"ifFalseActivities": [
						{
							"name": "Dummy",
							"type": "Wait",
							"dependsOn": [],
							"userProperties": [],
							"typeProperties": {
								"waitTimeInSeconds": 1
							}
						}
					],
					"ifTrueActivities": [
						{
							"name": "Copy xlsx to green case specialist csv file",
							"type": "Copy",
							"dependsOn": [],
							"policy": {
								"timeout": "0.12:00:00",
								"retry": 0,
								"retryIntervalInSeconds": 30,
								"secureOutput": false,
								"secureInput": false
							},
							"userProperties": [],
							"typeProperties": {
								"source": {
									"type": "ExcelSource",
									"storeSettings": {
										"type": "AzureBlobFSReadSettings",
										"enablePartitionDiscovery": false
									}
								},
								"sink": {
									"type": "DelimitedTextSink",
									"storeSettings": {
										"type": "AzureBlobFSWriteSettings"
									},
									"formatSettings": {
										"type": "DelimitedTextWriteSettings",
										"quoteAllText": true,
										"fileExtension": ".csv"
									}
								},
								"enableStaging": false,
								"translator": {
									"type": "TabularTranslator",
									"typeConversion": false,
									"typeConversionSettings": {
										"allowDataTruncation": true,
										"treatBooleanAsNumber": false
									}
								}
							},
							"inputs": [
								{
									"referenceName": "ds_odw_raw_green_case_specialist_archive_src",
									"type": "DatasetReference"
								}
							],
							"outputs": [
								{
									"referenceName": "ds_odw_raw_green_specialist_case_dest",
									"type": "DatasetReference"
								}
							]
						}
					]
				}
			}
		],
		"parameters": {
			"Folder_Path": {
				"type": "string",
				"defaultValue": "ODW/Green_Specialist_Case"
			}
		},
		"folder": {
			"name": "green_specialist_case/layers/0-raw"
		},
		"annotations": []
	}
}
