{
	"name": "MPESC SQL Server",
	"properties": {
		"annotations": [],
		"type": "AzureSqlDatabase",
		"typeProperties": {
			"server": "pins-sql-peas-primary-dev.database.windows.net",
			"database": "pins-sqldb-peas-dev",
			"encrypt": "mandatory",
			"trustServerCertificate": false,
			"authenticationType": "SQL",
			"userName": "peas_app_ZXzkE0vP",
			"password": {
				"type": "AzureKeyVaultSecret",
				"store": {
					"referenceName": "ls_kv",
					"type": "LinkedServiceReference"
				},
				"secretName": "mpesc-sql-password",
				"secretVersion": "3550da9bc2014255a52e8227cee59f6e"
			}
		},
		"connectVia": {
			"referenceName": "AutoResolveIntegrationRuntime",
			"type": "IntegrationRuntimeReference"
		}
	},
	"type": "Microsoft.Synapse/workspaces/linkedservices"
}